[
    {
        "path": "404.html",
        "type": "file",
        "md5": "aa24de70590b27817b1c980e2e43a12d"
    },
    {
        "path": "assets",
        "type": "directory",
        "md5": false
    },
    {
        "path": "assets/css",
        "type": "directory",
        "md5": false
    },
    {
        "path": "/assets/css/editor.css",
        "type": "file",
        "md5": "4202808df745f2ac7ab250606fa0d272"
    },
    {
        "path": "/assets/css/main.css",
        "type": "file",
        "md5": "fa238f48f9a2ab93b0c59a116e831bca"
    },
    {
        "path": "/assets/css/style.css",
        "type": "file",
        "md5": "11bee19e86e8eda2cf9a60efd975666d"
    },
    {
        "path": "assets/dynamic",
        "type": "directory",
        "md5": false
    },
    {
        "path": "assets/js",
        "type": "directory",
        "md5": false
    },
    {
        "path": "/assets/js/scripts.js",
        "type": "file",
        "md5": "e9e5c3efbaa696d1490988cf5b30e23b"
    },
    {
        "path": "/assets/js/scripts.min.js",
        "type": "file",
        "md5": "700105c316933a8202041b6415abb233"
    },
    {
        "path": "/assets/js/svg-fix.js",
        "type": "file",
        "md5": "9b7d020c55e2b4f77ab40c97f88f9ff4"
    },
    {
        "path": "/assets/js/svg-map.js",
        "type": "file",
        "md5": "ff4392540fcf4c3d3f5e03806e112816"
    },
    {
        "path": "assets/svg",
        "type": "directory",
        "md5": false
    },
    {
        "path": "/assets/svg/svg-map.svg",
        "type": "file",
        "md5": "cf04dfd5c3cc64e0be44692fe7d976a6"
    },
    {
        "path": "authors",
        "type": "directory",
        "md5": false
    },
    {
        "path": "authors/karem",
        "type": "directory",
        "md5": false
    },
    {
        "path": "/authors/karem/index.html",
        "type": "file",
        "md5": "41eab5da8ee140cb51eb646433e341a6"
    },
    {
        "path": "feed.json",
        "type": "file",
        "md5": "c6b4714193db0e2984f59557bddeea8b"
    },
    {
        "path": "feed.xml",
        "type": "file",
        "md5": "1bc8fa9ea5fb7cee83abad0e855f15e6"
    },
    {
        "path": "index.html",
        "type": "file",
        "md5": "67a21f1748f004f29a894e3e21fcad9a"
    },
    {
        "path": "media",
        "type": "directory",
        "md5": false
    },
    {
        "path": "media/posts",
        "type": "directory",
        "md5": false
    },
    {
        "path": "media/posts/1",
        "type": "directory",
        "md5": false
    },
    {
        "path": "media/posts/1/gallery",
        "type": "directory",
        "md5": false
    },
    {
        "path": "/media/posts/1/gallery/shrk-tnZyf-mkyft-fy-dby-2-thumbnail.jpg",
        "type": "file",
        "md5": "7a39468c4649bc62f8fde6930d45e078"
    },
    {
        "path": "/media/posts/1/gallery/shrk-tnZyf-mkyft-fy-dby-2.jpg",
        "type": "file",
        "md5": "97ef56f66506a8d39a780814a1597a58"
    },
    {
        "path": "media/posts/2",
        "type": "directory",
        "md5": false
    },
    {
        "path": "media/posts/2/gallery",
        "type": "directory",
        "md5": false
    },
    {
        "path": "/media/posts/2/gallery/12-244-thumbnail.jpg",
        "type": "file",
        "md5": "148123633ea90beebdf5e34a7b941e25"
    },
    {
        "path": "/media/posts/2/gallery/12-244.jpg",
        "type": "file",
        "md5": "94226194cfd56cd51ce654ffc4d4d018"
    },
    {
        "path": "media/posts/3",
        "type": "directory",
        "md5": false
    },
    {
        "path": "media/posts/3/gallery",
        "type": "directory",
        "md5": false
    },
    {
        "path": "/media/posts/3/gallery/saar-shrk-tnZyf-mkyft-fy-dby-thumbnail.jpg",
        "type": "file",
        "md5": "5095e040cfa2472c74b8ac6da6711450"
    },
    {
        "path": "/media/posts/3/gallery/saar-shrk-tnZyf-mkyft-fy-dby.jpg",
        "type": "file",
        "md5": "f3a6b174d9cfb7a4e0ce8f8f9668f4dd"
    },
    {
        "path": "media/posts/4",
        "type": "directory",
        "md5": false
    },
    {
        "path": "media/posts/4/gallery",
        "type": "directory",
        "md5": false
    },
    {
        "path": "/media/posts/4/gallery/12-230-thumbnail.jpg",
        "type": "file",
        "md5": "584e8498fac2e3cfd877e06994313375"
    },
    {
        "path": "/media/posts/4/gallery/12-230.jpg",
        "type": "file",
        "md5": "b4e61bf5d92567e981191e5cac870601"
    },
    {
        "path": "media/posts/5",
        "type": "directory",
        "md5": false
    },
    {
        "path": "media/posts/5/gallery",
        "type": "directory",
        "md5": false
    },
    {
        "path": "/media/posts/5/gallery/12-21-thumbnail.jpg",
        "type": "file",
        "md5": "757f9e948ca7baa7b3d21177823f0d95"
    },
    {
        "path": "/media/posts/5/gallery/12-21.jpg",
        "type": "file",
        "md5": "0ac94ce68d86b11a8d672d324121bae4"
    },
    {
        "path": "media/website",
        "type": "directory",
        "md5": false
    },
    {
        "path": "media/website/responsive",
        "type": "directory",
        "md5": false
    },
    {
        "path": "/media/website/responsive/saar-shrk-tnZyf-mkyft-fy-dby-2xl.jpg",
        "type": "file",
        "md5": "e96cdf98c8a7e157f5fb16c923b73a04"
    },
    {
        "path": "/media/website/responsive/saar-shrk-tnZyf-mkyft-fy-dby-lg.jpg",
        "type": "file",
        "md5": "e96cdf98c8a7e157f5fb16c923b73a04"
    },
    {
        "path": "/media/website/responsive/saar-shrk-tnZyf-mkyft-fy-dby-md.jpg",
        "type": "file",
        "md5": "e9544cf6daddfafbc1da626901ba8eb3"
    },
    {
        "path": "/media/website/responsive/saar-shrk-tnZyf-mkyft-fy-dby-sm.jpg",
        "type": "file",
        "md5": "36b3a8672fbf8816fee5bf620fba2203"
    },
    {
        "path": "/media/website/responsive/saar-shrk-tnZyf-mkyft-fy-dby-xl.jpg",
        "type": "file",
        "md5": "e96cdf98c8a7e157f5fb16c923b73a04"
    },
    {
        "path": "/media/website/responsive/saar-shrk-tnZyf-mkyft-fy-dby-xs.jpg",
        "type": "file",
        "md5": "0df79464f7d3a9ab46b5099cb5bade4f"
    },
    {
        "path": "/media/website/saar-shrk-tnZyf-mkyft-fy-dby.jpg",
        "type": "file",
        "md5": "f3a6b174d9cfb7a4e0ce8f8f9668f4dd"
    },
    {
        "path": "qrb-shrk-tnzyf-mkyft",
        "type": "directory",
        "md5": false
    },
    {
        "path": "/qrb-shrk-tnzyf-mkyft/index.html",
        "type": "file",
        "md5": "ded3921e3949a372f1783b03b76640d4"
    },
    {
        "path": "robots.txt",
        "type": "file",
        "md5": "572e150f719203925b02038f365edf69"
    },
    {
        "path": "rqm-shrk-tnzyf-mkyft",
        "type": "directory",
        "md5": false
    },
    {
        "path": "/rqm-shrk-tnzyf-mkyft/index.html",
        "type": "file",
        "md5": "61f6bd7923753c8dded96603b594aa5d"
    },
    {
        "path": "shrk-jly-rkhm",
        "type": "directory",
        "md5": false
    },
    {
        "path": "/shrk-jly-rkhm/index.html",
        "type": "file",
        "md5": "b79d547d409950922692c60e6b710d3f"
    },
    {
        "path": "shrk-jly-rkhm-fy-bwzby",
        "type": "directory",
        "md5": false
    },
    {
        "path": "/shrk-jly-rkhm-fy-bwzby/index.html",
        "type": "file",
        "md5": "0c6b019a1eeb15d3d7fa93a9c6a84450"
    },
    {
        "path": "shrk-tnzyf-mkyft",
        "type": "directory",
        "md5": false
    },
    {
        "path": "/shrk-tnzyf-mkyft/index.html",
        "type": "file",
        "md5": "c551ed621455dafb286f23842219aa68"
    },
    {
        "path": "sitemap.xml",
        "type": "file",
        "md5": "08cb9210cd0ee4e112ad78b346d40eee"
    },
    {
        "path": "sitemap.xsl",
        "type": "file",
        "md5": "03c2f9a7fdcc46ff05c435907614a0b8"
    },
    {
        "path": "tags",
        "type": "directory",
        "md5": false
    },
    {
        "path": "/tags/index.html",
        "type": "file",
        "md5": "333723f94de726e7a46604ac4dcad1dc"
    }
]